{
  "version": "1.0",
  "lastUpdated": "2025-12-09T00:08:17.199Z",
  "modules": {
    "quiz": {
      "name": "Welcher Coaching-Weg passt zu dir?",
      "active": false,
      "page": "index.html"
    },
    "angebote": {
      "name": "Meine Angebote",
      "active": false,
      "page": "index.html"
    },
    "ueber": {
      "name": "Mein Herz führt mich durchs Leben",
      "active": false,
      "page": "index.html"
    },
    "methoden": {
      "name": "Mit welchen Methoden ich arbeite",
      "active": false,
      "page": "index.html"
    },
    "kontakt": {
      "name": "Bereit für den ersten Schritt?",
      "active": false,
      "page": "index.html"
    },
    "blog": {
      "name": "Neugierig geworden?",
      "active": false,
      "page": "index.html"
    }
  },
  "feedback": []
}